CTkMenuBar/__init__.py
CTkMenuBar/dropdown_menu.py
CTkMenuBar/menu_bar.py
CTkMenuBar/title_menu_win.py
ctkmenubar-0.9.dist-info/licenses/LICENSE
ctkmenubar-0.9.dist-info/METADATA
ctkmenubar-0.9.dist-info/WHEEL
ctkmenubar-0.9.dist-info/dependency_links.txt
ctkmenubar-0.9.dist-info/top_level.txt
ctkmenubar-0.9.dist-info/RECORD
