Metadata-Version: 2.4
Name: CTkMenuBar
Version: 0.9
Summary: Customtkinter Menu Widget
Home-page: https://github.com/Akascape/CTkMenuBar
Author: Akash Bora
License: Creative Commons Zero v1.0 Universal
Keywords: customtkinter,customtkinter-menu,ctkmenubar,titlemenu,menubar,tkinter,menu-widget,tkinter-gui
Classifier: License :: CC0 1.0 Universal (CC0 1.0) Public Domain Dedication
Classifier: Programming Language :: Python :: 3
Classifier: Operating System :: OS Independent
Requires-Python: >=3.6
License-File: LICENSE
Requires-Dist: customtkinter
Dynamic: author
Dynamic: classifier
Dynamic: description
Dynamic: description-content-type
Dynamic: home-page
Dynamic: keywords
Dynamic: license
Dynamic: license-file
Dynamic: requires-dist
Dynamic: requires-python
Dynamic: summary
